pyinduct/__init__.py
pyinduct/core.py
pyinduct/eigenfunctions.py
pyinduct/feedback.py
pyinduct/placeholder.py
pyinduct/registry.py
pyinduct/run_tests.py
pyinduct/shapefunctions.py
pyinduct/simulation.py
pyinduct/trajectory.py
pyinduct/utils.py
pyinduct/version.py
pyinduct/visualization.py
pyinduct/examples/__init__.py
pyinduct/examples/diff_eq_multiple_inputs.py
pyinduct/examples/euler_bernoulli_beam.py
pyinduct/examples/pipe_flow.py
pyinduct/examples/rad_eq_const_coeff.py
pyinduct/examples/rad_eq_diri_fem.py
pyinduct/examples/rad_eq_in_domain.py
pyinduct/examples/rad_eq_minimal.py
pyinduct/examples/rad_eq_var_coeff.py
pyinduct/examples/transport_system.py
pyinduct/examples/string_with_mass/__init__.py
pyinduct/examples/string_with_mass/control.py
pyinduct/examples/string_with_mass/main.py
pyinduct/examples/string_with_mass/system.py
pyinduct/examples/string_with_mass/utils.py
pyinduct/examples/string_with_mass/observer_evp_scripts/__init__.py
pyinduct/examples/string_with_mass/observer_evp_scripts/evp_dual.py
pyinduct/examples/string_with_mass/observer_evp_scripts/evp_dual_nf.py
pyinduct/examples/string_with_mass/observer_evp_scripts/evp_primal.py
pyinduct/examples/string_with_mass/observer_evp_scripts/evp_primal_nf.py
pyinduct/examples/string_with_mass/observer_evp_scripts/modal_approximation.py
pyinduct/hyperbolic/__init__.py
pyinduct/hyperbolic/feedforward.py
pyinduct/parabolic/__init__.py
pyinduct/parabolic/control.py
pyinduct/parabolic/feedforward.py
pyinduct/parabolic/general.py
pyinduct/parabolic/trajectory.py
pyinduct/tests/__init__.py
pyinduct/tests/test_control.py
pyinduct/tests/test_core.py
pyinduct/tests/test_eigenfunctions.py
pyinduct/tests/test_examples.py
pyinduct/tests/test_placeholder.py
pyinduct/tests/test_registry.py
pyinduct/tests/test_shapefunctions.py
pyinduct/tests/test_simulation.py
pyinduct/tests/test_string_with_mass.py
pyinduct/tests/test_timings.py
pyinduct/tests/test_trajectory.py
pyinduct/tests/test_utils.py
pyinduct-0.5.2.dist-info/AUTHORS.rst
pyinduct-0.5.2.dist-info/LICENSE
pyinduct-0.5.2.dist-info/METADATA
pyinduct-0.5.2.dist-info/WHEEL
pyinduct-0.5.2.dist-info/top_level.txt
pyinduct-0.5.2.dist-info/RECORD
