Metadata-Version: 2.1
Name: pyinduct
Version: 0.5.2
Summary: Toolbox for control and observer design for infinite dimensional systems.
Home-page: https://github.com/pyinduct/pyinduct/
Author: Stefan Ecklebe, Marcus Riesmeier
Author-email: stefan.ecklebe@tu-dresden.de, marcus.riesmeier@umit.at
License: BSD 3-Clause License
Download-URL: https://github.com/pyinduct/pyinduct/releases
Project-URL: Documentation, https://pyinduct.readthedocs.org
Project-URL: Source Code, https://github.com/pyinduct/pyinduct/
Project-URL: Bug Tracker, https://github.com/pyinduct/pyinduct/issues
Keywords: distributed-parameter-systems control observer simulation
Platform: UNKNOWN
Classifier: Development Status :: 4 - Beta
Classifier: Intended Audience :: Science/Research
Classifier: Intended Audience :: Developers
Classifier: Topic :: Scientific/Engineering
Classifier: License :: OSI Approved :: BSD License
Classifier: Operating System :: OS Independent
Classifier: Natural Language :: English
Classifier: Programming Language :: Python :: 3.5
Classifier: Programming Language :: Python :: 3.6
Classifier: Programming Language :: Python :: 3.7
Classifier: Programming Language :: Python :: 3.8
Classifier: Programming Language :: Python :: 3.9
Classifier: Programming Language :: Python :: 3.10
Requires-Python: >=3.5
License-File: LICENSE
License-File: AUTHORS.rst
Requires-Dist: numpy (>=1.10.2)
Requires-Dist: scipy (>=0.16.1)
Requires-Dist: sympy (>=1.0)
Requires-Dist: wheel (>=0.23.0)
Requires-Dist: pyqtgraph (>=0.9.10)
Requires-Dist: PyOpenGL (>=3.1.0)
Requires-Dist: matplotlib (>=1.5.0)
Requires-Dist: pip (>=19.3)
Requires-Dist: PyQt5 (>=5.7.0)
Provides-Extra: docs
Requires-Dist: sphinx (>=3.2.1) ; extra == 'docs'
Requires-Dist: sphinx-autoapi (>=1.5.0) ; extra == 'docs'
Requires-Dist: sphinx-rtd-theme (>=0.5.0) ; extra == 'docs'
Provides-Extra: tests
Requires-Dist: codecov (>=2.0.15) ; extra == 'tests'
